Workbook

Sheet Planilha1
B1: Jan | C1: Fev | D1: Mar | E1: Abr | F1: Mai | G1: Jun | H1: Jul | I1: Ago | J1: Set | K1: Out | L1: Nov | M1: Dez | N1: Total | O1: Part. (%)
A2: TOTAL GERAL | B2: =SUM(B5:B7,B10:B19,B22:B31,B34:B41,B43:B50,B52:B59,B61:B68,B70:B76,B78:B85,B87:B94,B96:B103,B105:B112,B114:B121,B123:B130,B132:B139,B141:B148,B150:B157,B159:B166,B168:B175,B177:B184,B186:B193,B195:B202,B204:B211,B213:B220,B222:B229,B231:B237,B239:B243,B245:B252,B254:B263,B265:B275,B277:B292,B294:B299,B301:B305,B307:B313,B316:B323,B325:B332,B334:B341,B343:B350,B352:B359,B361,B363:B367,B369:B373,B375:B383) -> 82466.717 | C2: =SUM(C5:C7,C10:C19,C22:C31,C34:C41,C43:C50,C52:C59,C61:C68,C70:C76,C78:C85,C87:C94,C96:C103,C105:C112,C114:C121,C123:C130,C132:C139,C141:C148,C150:C157,C159:C166,C168:C175,C177:C184,C186:C193,C195:C202,C204:C211,C213:C220,C222:C229,C231:C237,C239:C243,C245:C252,C254:C263,C265:C275,C277:C292,C294:C299,C301:C305,C307:C313,C316:C323,C325:C332,C334:C341,C343:C350,C352:C359,C361,C363:C367,C369:C373,C375:C383) -> 202956.06 | D2: =SUM(D5:D7,D10:D19,D22:D31,D34:D41,D43:D50,D52:D59,D61:D68,D70:D76,D78:D85,D87:D94,D96:D103,D105:D112,D114:D121,D123:D130,D132:D139,D141:D148,D150:D157,D159:D166,D168:D175,D177:D184,D186:D193,D195:D202,D204:D211,D213:D220,D222:D229,D231:D237,D239:D243,D245:D252,D254:D263,D265:D275,D277:D292,D294:D299,D301:D305,D307:D313,D316:D323,D325:D332,D334:D341,D343:D350,D352:D359,D361,D363:D367,D369:D373,D375:D383) -> 204123.35 | E2: =SUM(E5:E7,E10:E19,E22:E31,E34:E41,E43:E50,E52:E59,E61:E68,E70:E76,E78:E85,E87:E94,E96:E103,E105:E112,E114:E121,E123:E130,E132:E139,E141:E148,E150:E157,E159:E166,E168:E175,E177:E184,E186:E193,E195:E202,E204:E211,E213:E220,E222:E229,E231:E237,E239:E243,E245:E252,E254:E263,E265:E275,E277:E292,E294:E299,E301:E305,E307:E313,E316:E323,E325:E332,E334:E341,E343:E350,E352:E359,E361,E363:E367,E369:E373,E375:E383) -> 206223.71 | F2: =SUM(F5:F7,F10:F19,F22:F31,F34:F41,F43:F50,F52:F59,F61:F68,F70:F76,F78:F85,F87:F94,F96:F103,F105:F112,F114:F121,F123:F130,F132:F139,F141:F148,F150:F157,F159:F166,F168:F175,F177:F184,F186:F193,F195:F202,F204:F211,F213:F220,F222:F229,F231:F237,F239:F243,F245:F252,F254:F263,F265:F275,F277:F292,F294:F299,F301:F305,F307:F313,F316:F323,F325:F332,F334:F341,F343:F350,F352:F359,F361,F363:F367,F369:F373,F375:F383) -> 177140.59 | G2: =SUM(G5:G7,G10:G19,G22:G31,G34:G41,G43:G50,G52:G59,G61:G68,G70:G76,G78:G85,G87:G94,G96:G103,G105:G112,G114:G121,G123:G130,G132:G139,G141:G148,G150:G157,G159:G166,G168:G175,G177:G184,G186:G193,G195:G202,G204:G211,G213:G220,G222:G229,G231:G237,G239:G243,G245:G252,G254:G263,G265:G275,G277:G292,G294:G299,G301:G305,G307:G313,G316:G323,G325:G332,G334:G341,G343:G350,G352:G359,G361,G363:G367,G369:G373,G375:G383) -> 208980.2 | H2: =SUM(H5:H7,H10:H19,H22:H31,H34:H41,H43:H50,H52:H59,H61:H68,H70:H76,H78:H85,H87:H94,H96:H103,H105:H112,H114:H121,H123:H130,H132:H139,H141:H148,H150:H157,H159:H166,H168:H175,H177:H184,H186:H193,H195:H202,H204:H211,H213:H220,H222:H229,H231:H237,H239:H243,H245:H252,H254:H263,H265:H275,H277:H292,H294:H299,H301:H305,H307:H313,H316:H323,H325:H332,H334:H341,H343:H350,H352:H359,H361,H363:H367,H369:H373,H375:H383) -> 204466.13 | I2: =SUM(I5:I7,I10:I19,I22:I31,I34:I41,I43:I50,I52:I59,I61:I68,I70:I76,I78:I85,I87:I94,I96:I103,I105:I112,I114:I121,I123:I130,I132:I139,I141:I148,I150:I157,I159:I166,I168:I175,I177:I184,I186:I193,I195:I202,I204:I211,I213:I220,I222:I229,I231:I237,I239:I243,I245:I252,I254:I263,I265:I275,I277:I292,I294:I299,I301:I305,I307:I313,I316:I323,I325:I332,I334:I341,I343:I350,I352:I359,I361,I363:I367,I369:I373,I375:I383) -> 175138.26 | ... N2: =SUM(N5:N7,N10:N19,N22:N31,N34:N41,N43:N50,N52:N59,N61:N68,N70:N76,N78:N85,N87:N94,N96:N103,N105:N112,N114:N121,N123:N130,N132:N139,N141:N148,N150:N157,N159:N166,N168:N175,N177:N184,N186:N193,N195:N202,N204:N211,N213:N220,N222:N229,N231:N237,N239:N243,N245:N252,N254:N263,N265:N275,N277:N292,N294:N299,N301:N305,N307:N313,N316:N323,N325:N332,N334:N341,N343:N350,N352:N359,N361,N363:N367,N369:N373,N375:N383) -> 1974624.2 | O2: =N2/$N$2*100 -> 100
A3: PESSOAL (CLT e PJ recorrente) | B3: =SUM(B5:B7,B10:B19) -> 42695.126 | C3: =SUM(C5:C7,C10:C19) -> 42578.288 | D3: =SUM(D5:D7,D10:D19) -> 54795.525 | E3: =SUM(E5:E7,E10:E19) -> 54795.525 | F3: =SUM(F5:F7,F10:F19) -> 54795.525 | G3: =SUM(G5:G7,G10:G19) -> 54795.525 | H3: =SUM(H5:H7,H10:H19) -> 54795.525 | I3: =SUM(I5:I7,I10:I19) -> 54795.525 | ... N3: =SUM(N5:N7,N10:N19) -> 633228.67 | O3: =N3/$N$2*100 -> 32.068313
A4: Folha CLT | B4: =SUM(B5:B7) -> 14436.036 | C4: =SUM(C5:C7) -> 14319.198 | D4: =SUM(D5:D7) -> 16236.435 | E4: =SUM(E5:E7) -> 16236.435 | F4: =SUM(F5:F7) -> 16236.435 | G4: =SUM(G5:G7) -> 16236.435 | H4: =SUM(H5:H7) -> 16236.435 | I4: =SUM(I5:I7) -> 16236.435 | ... N4: =SUM(N5:N7) -> 191119.59 | O4: =N4/$N$2*100 -> 9.6787829
A5: Analista administrativo e financeiro - Isabela Rolim | B5: =2523.92*1.8 -> 4543.056 | C5: =2523.92*1.8 -> 4543.056 | D5: =3488.9*1.8 -> 6280.02 | E5: =3488.9*1.8 -> 6280.02 | F5: =3488.9*1.8 -> 6280.02 | G5: =3488.9*1.8 -> 6280.02 | H5: =3488.9*1.8 -> 6280.02 | I5: =3488.9*1.8 -> 6280.02 | J5: =3488.9*1.8 -> 6280.02 | K5: =3488.9*1.8 -> 6280.02 | ... M5: =3488.9*1.8 -> 6280.02 | N5: =SUM(B5:M5) -> 71886.312 | O5: =N5/$N$2*100 -> 3.640506
A6: Assistente Comercial / administrativo - Emmanuel Pires | B6: =2007.2*1.8 -> 3612.96 | C6: =2007.2*1.8 -> 3612.96 | D6: 3793.2333 | E6: 3793.2333 | F6: 3793.2333 | G6: 3793.2333 | H6: 3793.2333 | I6: 3793.2333 | J6: 3793.2333 | K6: 3793.2333 | L6: 3793.2333 | M6: 3793.2333 | N6: =SUM(B6:M6) -> 45158.253 | O6: =N6/$N$2*100 -> 2.286929
A7: Consultora Pedagógica (Analista) - Raissa Fernandes | B7: =3488.9*1.8 -> 6280.02 | C7: =3423.99*1.8 -> 6163.182 | D7: =3423.99*1.8 -> 6163.182 | E7: =3423.99*1.8 -> 6163.182 | F7: =3423.99*1.8 -> 6163.182 | G7: =3423.99*1.8 -> 6163.182 | H7: =3423.99*1.8 -> 6163.182 | I7: =3423.99*1.8 -> 6163.182 | J7: =3423.99*1.8 -> 6163.182 | ... M7: =3423.99*1.8 -> 6163.182 | N7: =SUM(B7:M7) -> 74075.022 | O7: =N7/$N$2*100 -> 3.7513479
A9: PJs recorrentes | B9: =SUM(B10:B19) -> 28259.09 | C9: =SUM(C10:C19) -> 28259.09 | D9: =SUM(D10:D19) -> 38559.09 | E9: =SUM(E10:E19) -> 38559.09 | F9: =SUM(F10:F19) -> 38559.09 | G9: =SUM(G10:G19) -> 38559.09 | H9: =SUM(H10:H19) -> 38559.09 | I9: =SUM(I10:I19) -> 38559.09 | ... N9: =SUM(N10:N19) -> 442109.08 | O9: =N9/$N$2*100 -> 22.38953
A10: Consultor Primeira infância - Layla Ramos | B10: 5445.91 | C10: 5445.91 | D10: 5445.91 | E10: 5445.91 | F10: 5445.91 | G10: 5445.91 | H10: 5445.91 | I10: 5445.91 | J10: 5445.91 | K10: 5445.91 | L10: 5445.91 | M10: 5445.91 | N10: =SUM(B10:M10) -> 65350.92 | O10: =N10/$N$2*100 -> 3.3095371
A11: Consultor Fund 1 - Jhon Jarisson | B11: 5445.91 | C11: 5445.91 | D11: 5445.91 | E11: 5445.91 | F11: 5445.91 | G11: 5445.91 | H11: 5445.91 | I11: 5445.91 | J11: 5445.91 | K11: 5445.91 | L11: 5445.91 | M11: 5445.91 | N11: =SUM(B11:M11) -> 65350.92 | O11: =N11/$N$2*100 -> 3.3095371
A12: Consultor Fund 1 - Bia Andrade | B12: 5667.27 | C12: 5667.27 | D12: 5667.27 | E12: 5667.27 | F12: 5667.27 | G12: 5667.27 | H12: 5667.27 | I12: 5667.27 | J12: 5667.27 | K12: 5667.27 | L12: 5667.27 | M12: 5667.27 | N12: =SUM(B12:M12) -> 68007.24 | O12: =N12/$N$2*100 -> 3.4440599
A13: Analista editorial Infantil - Belinha | B13: 5000 | C13: 5000 | D13: 5000 | E13: 5000 | F13: 5000 | G13: 5000 | H13: 5000 | I13: 5000 | J13: 5000 | K13: 5000 | L13: 5000 | M13: 5000 | N13: =SUM(B13:M13) -> 60000 | O13: =N13/$N$2*100 -> 3.0385529
A14: Consultor organizacional - Renato Assis | B14: 6000 | C14: 6000 | D14: 6000 | E14: 6000 | F14: 6000 | G14: 6000 | H14: 6000 | I14: 6000 | J14: 6000 | K14: 6000 | L14: 6000 | M14: 6000 | N14: =SUM(B14:M14) -> 72000 | O14: =N14/$N$2*100 -> 3.6462635
A15: Consultor de produção musical - Marcio | B15: 700 | C15: 700 | N15: =SUM(B15:M15) -> 1400 | O15: =N15/$N$2*100 -> 0.070899568
A16: Representação comercial - Região Norte | D16: 1500 | E16: 1500 | F16: 1500 | G16: 1500 | H16: 1500 | I16: 1500 | J16: 1500 | K16: 1500 | L16: 1500 | M16: 1500 | N16: =SUM(B16:M16) -> 15000 | O16: =N16/$N$2*100 -> 0.75963823
A17: Analista editorial Fund 1 - a contratar | D17: 3000 | E17: 3000 | F17: 3000 | G17: 3000 | H17: 3000 | I17: 3000 | J17: 3000 | K17: 3000 | L17: 3000 | M17: 3000 | N17: =SUM(B17:M17) -> 30000 | O17: =N17/$N$2*100 -> 1.5192765
A18: Representante comercial - a contratar | D18: 4000 | E18: 4000 | F18: 4000 | G18: 4000 | H18: 4000 | I18: 4000 | J18: 4000 | K18: 4000 | L18: 4000 | M18: 4000 | N18: =SUM(B18:M18) -> 40000 | O18: =N18/$N$2*100 -> 2.0257019
A19: Analista de marketing - a contratar | D19: 2500 | E19: 2500 | F19: 2500 | G19: 2500 | H19: 2500 | I19: 2500 | J19: 2500 | K19: 2500 | L19: 2500 | M19: 2500 | N19: =SUM(B19:M19) -> 25000 | O19: =N19/$N$2*100 -> 1.2660637
A20: PRODUÇÃO PEDAGÓGICA & EDITORIAL (Conteúdo) | B20: =SUM(B22:B31,B34:B41,B43:B50,B52:B59,B61:B68,B70:B76,B78:B85,B87:B94,B96:B103,B105:B112,B114:B121,B123:B130,B132:B139,B141:B148,B150:B157,B159:B166,B168:B175,B177:B184,B186:B193,B195:B202,B204:B211,B213:B220,B222:B229,B231:B237,B239:B243) -> 2100 | C20: =SUM(C22:C31,C34:C41,C43:C50,C52:C59,C61:C68,C70:C76,C78:C85,C87:C94,C96:C103,C105:C112,C114:C121,C123:C130,C132:C139,C141:C148,C150:C157,C159:C166,C168:C175,C177:C184,C186:C193,C195:C202,C204:C211,C213:C220,C222:C229,C231:C237,C239:C243) -> 66221.05 | D20: =SUM(D22:D31,D34:D41,D43:D50,D52:D59,D61:D68,D70:D76,D78:D85,D87:D94,D96:D103,D105:D112,D114:D121,D123:D130,D132:D139,D141:D148,D150:D157,D159:D166,D168:D175,D177:D184,D186:D193,D195:D202,D204:D211,D213:D220,D222:D229,D231:D237,D239:D243) -> 40432.713 | E20: =SUM(E22:E31,E34:E41,E43:E50,E52:E59,E61:E68,E70:E76,E78:E85,E87:E94,E96:E103,E105:E112,E114:E121,E123:E130,E132:E139,E141:E148,E150:E157,E159:E166,E168:E175,E177:E184,E186:E193,E195:E202,E204:E211,E213:E220,E222:E229,E231:E237,E239:E243) -> 32199.733 | F20: =SUM(F22:F31,F34:F41,F43:F50,F52:F59,F61:F68,F70:F76,F78:F85,F87:F94,F96:F103,F105:F112,F114:F121,F123:F130,F132:F139,F141:F148,F150:F157,F159:F166,F168:F175,F177:F184,F186:F193,F195:F202,F204:F211,F213:F220,F222:F229,F231:F237,F239:F243) -> 5085.3333 | G20: =SUM(G22:G31,G34:G41,G43:G50,G52:G59,G61:G68,G70:G76,G78:G85,G87:G94,G96:G103,G105:G112,G114:G121,G123:G130,G132:G139,G141:G148,G150:G157,G159:G166,G168:G175,G177:G184,G186:G193,G195:G202,G204:G211,G213:G220,G222:G229,G231:G237,G239:G243) -> 9685.3333 | H20: =SUM(H22:H31,H34:H41,H43:H50,H52:H59,H61:H68,H70:H76,H78:H85,H87:H94,H96:H103,H105:H112,H114:H121,H123:H130,H132:H139,H141:H148,H150:H157,H159:H166,H168:H175,H177:H184,H186:H193,H195:H202,H204:H211,H213:H220,H222:H229,H231:H237,H239:H243) -> 1965.3333 | I20: =SUM(I22:I31,I34:I41,I43:I50,I52:I59,I61:I68,I70:I76,I78:I85,I87:I94,I96:I103,I105:I112,I114:I121,I123:I130,I132:I139,I141:I148,I150:I157,I159:I166,I168:I175,I177:I184,I186:I193,I195:I202,I204:I211,I213:I220,I222:I229,I231:I237,I239:I243) -> 37619.384 | ... N20: =SUM(N22:N31,N34:N41,N43:N50,N52:N59,N61:N68,N70:N76,N78:N85,N87:N94,N96:N103,N105:N112,N114:N121,N123:N130,N132:N139,N141:N148,N150:N157,N159:N166,N168:N175,N177:N184,N186:N193,N195:N202,N204:N211,N213:N220,N222:N229,N231:N237,N239:N243) -> 294442.01 | O20: =N20/$N$2*100 -> 14.911294
A21: PAIDEIA INFANTIL | B21: =SUM(B22:B31) -> 100 | C21: =SUM(C22:C31) -> 26866.667 | D21: =SUM(D22:D31) -> 5105.3333 | E21: =SUM(E22:E31) -> 5105.3333 | F21: =SUM(F22:F31) -> 3085.3333 | G21: =SUM(G22:G31) -> 3085.3333 | H21: =SUM(H22:H31) -> 1965.3333 | I21: =SUM(I22:I31) -> 933.33333 | ... N21: =SUM(N22:N31) -> 49980 | O21: =N21/$N$2*100 -> 2.5311146
A22: Autoria Paideia - Infantil Priscila | C22: 6140 | N22: =SUM(B22:M22) -> 6140 | O22: =N22/$N$2*100 -> 0.31094525
A23: Autoria Paideia - Infantil Katarina | C23: 4320 | N23: =SUM(B23:M23) -> 4320 | O23: =N23/$N$2*100 -> 0.21877581
A24: Autoria Paideia – Infantil Jhon | C24: 3000 | D24: =5160/5 -> 1032 | E24: =5160/5 -> 1032 | F24: =5160/5 -> 1032 | G24: =5160/5 -> 1032 | H24: =5160/5 -> 1032 | N24: =SUM(B24:M24) -> 8160 | O24: =N24/$N$2*100 -> 0.41324319
A25: Autoria Paideia – Infantil Layla | C25: 2020 | D25: 2020 | E25: 2020 | N25: =SUM(B25:M25) -> 6060 | O25: =N25/$N$2*100 -> 0.30689384
A26: Autoria Paideia - Finalização de pagamento do autor de tecnologia | C26: 8000 | N26: =SUM(B26:M26) -> 8000 | O26: =N26/$N$2*100 -> 0.40514039
A27: Revisão de contéudo Paideia - Infantil livro do aluno (Pag. por página diagramada no valor de R$ 3,50) | C27: =((3.5*200)*8)/5 -> 1120 | D27: =((3.5*200)*8)/5 -> 1120 | E27: =((3.5*200)*8)/5 -> 1120 | F27: =((3.5*200)*8)/5 -> 1120 | G27: =((3.5*200)*8)/5 -> 1120 | N27: =SUM(B27:M27) -> 5600 | O27: =N27/$N$2*100 -> 0.28359827
A28: Revisão de contéudo Paideia - Infantil livro do professor | N28: =SUM(B28:M28) -> 0 | O28: =N28/$N$2*100 -> 0
A29: Diagramação Paideia - Infantil (Livro 3 e 4 do aluno e todos os livros do professor) | C29: =(10000/12)*2 -> 1666.6667 | D29: =10000/12 -> 833.33333 | E29: =10000/12 -> 833.33333 | F29: =10000/12 -> 833.33333 | G29: =10000/12 -> 833.33333 | H29: =10000/12 -> 833.33333 | I29: =10000/12 -> 833.33333 | J29: =10000/12 -> 833.33333 | K29: =10000/12 -> 833.33333 | ... M29: =10000/12 -> 833.33333 | N29: =SUM(B29:M29) -> 10000 | O29: =N29/$N$2*100 -> 0.50642548
A30: Ilustração Paideia - Infantil | B30: 100 | C30: 100 | D30: 100 | E30: 100 | F30: 100 | G30: 100 | H30: 100 | I30: 100 | J30: 100 | K30: 100 | L30: 100 | M30: 100 | N30: =SUM(B30:M30) -> 1200 | O30: =N30/$N$2*100 -> 0.060771058
A31: Construção dos flashcards (geral) | C31: 500 | N31: =SUM(B31:M31) -> 500 | O31: =N31/$N$2*100 -> 0.025321274
A32: PRODUÇÃO FUDAMENTAL 1 (Pagamento de 50% em 2026 do 2º ano ao 5º ano) | B32: =SUM(B34:B41,B43:B50,B52:B59,B61:B68,B70:B76,B78:B85,B87:B94,B96:B103,B105:B112,B114:B121,B123:B130,B132:B139,B141:B148,B150:B157,B159:B166,B168:B175,B177:B184,B186:B193,B195:B202,B204:B211,B213:B220,B222:B229) -> 2000 | C32: =SUM(C34:C41,C43:C50,C52:C59,C61:C68,C70:C76,C78:C85,C87:C94,C96:C103,C105:C112,C114:C121,C123:C130,C132:C139,C141:C148,C150:C157,C159:C166,C168:C175,C177:C184,C186:C193,C195:C202,C204:C211,C213:C220,C222:C229) -> 36121.403 | D32: =SUM(D34:D41,D43:D50,D52:D59,D61:D68,D70:D76,D78:D85,D87:D94,D96:D103,D105:D112,D114:D121,D123:D130,D132:D139,D141:D148,D150:D157,D159:D166,D168:D175,D177:D184,D186:D193,D195:D202,D204:D211,D213:D220,D222:D229) -> 32094.4 | E32: =SUM(E34:E41,E43:E50,E52:E59,E61:E68,E70:E76,E78:E85,E87:E94,E96:E103,E105:E112,E114:E121,E123:E130,E132:E139,E141:E148,E150:E157,E159:E166,E168:E175,E177:E184,E186:E193,E195:E202,E204:E211,E213:E220,E222:E229) -> 27094.4 | F32: =SUM(F34:F41,F43:F50,F52:F59,F61:F68,F70:F76,F78:F85,F87:F94,F96:F103,F105:F112,F114:F121,F123:F130,F132:F139,F141:F148,F150:F157,F159:F166,F168:F175,F177:F184,F186:F193,F195:F202,F204:F211,F213:F220,F222:F229) -> 2000 | G32: =SUM(G34:G41,G43:G50,G52:G59,G61:G68,G70:G76,G78:G85,G87:G94,G96:G103,G105:G112,G114:G121,G123:G130,G132:G139,G141:G148,G150:G157,G159:G166,G168:G175,G177:G184,G186:G193,G195:G202,G204:G211,G213:G220,G222:G229) -> 0 | H32: =SUM(H34:H41,H43:H50,H52:H59,H61:H68,H70:H76,H78:H85,H87:H94,H96:H103,H105:H112,H114:H121,H123:H130,H132:H139,H141:H148,H150:H157,H159:H166,H168:H175,H177:H184,H186:H193,H195:H202,H204:H211,H213:H220,H222:H229) -> 0 | I32: =SUM(I34:I41,I43:I50,I52:I59,I61:I68,I70:I76,I78:I85,I87:I94,I96:I103,I105:I112,I114:I121,I123:I130,I132:I139,I141:I148,I150:I157,I159:I166,I168:I175,I177:I184,I186:I193,I195:I202,I204:I211,I213:I220,I222:I229) -> 36686.051 | ... N32: =SUM(N34:N41,N43:N50,N52:N59,N61:N68,N70:N76,N78:N85,N87:N94,N96:N103,N105:N112,N114:N121,N123:N130,N132:N139,N141:N148,N150:N157,N159:N166,N168:N175,N177:N184,N186:N193,N195:N202,N204:N211,N213:N220,N222:N229) -> 224796.05 | O32: =N32/$N$2*100 -> 11.384245
A33: Autoria - 1º Ano Fund 1 | B33: =SUM(B34:B41) -> 0 | C33: =SUM(C34:C41) -> 36121.403 | D33: =SUM(D34:D41) -> 32094.4 | E33: =SUM(E34:E41) -> 27094.4 | F33: =SUM(F34:F41) -> 0 | G33: =SUM(G34:G41) -> 0 | H33: =SUM(H34:H41) -> 0 | I33: =SUM(I34:I41) -> 1666.6667 | ... N33: =SUM(N34:N41) -> 100310.2 | O33: =N33/$N$2*100 -> 5.0799643
A34: Português | C34: =24000/3 -> 8000 | D34: =24000/3 -> 8000 | E34: =24000/3 -> 8000 | N34: =SUM(B34:M34) -> 24000 | O34: =N34/$N$2*100 -> 1.2154212
A35: Matemática | C35: 10000 | D35: 5000 | E35: 5000 | N35: =SUM(B35:M35) -> 20000 | O35: =N35/$N$2*100 -> 1.012851
A36: História | C36: 6288.07 | D36: 4861.0667 | E36: 4861.0667 | N36: =SUM(B36:M36) -> 16010.203 | O36: =N36/$N$2*100 -> 0.8107975
A37: Geografia | C37: 5000 | D37: 5000 | N37: =SUM(B37:M37) -> 10000 | O37: =N37/$N$2*100 -> 0.50642548
A38: Música | C38: 1666.6667 | D38: =5000/3 -> 1666.6667 | E38: =5000/3 -> 1666.6667 | N38: =SUM(B38:M38) -> 5000 | O38: =N38/$N$2*100 -> 0.25321274
A39: Arte | D39: 2400 | E39: 2400 | N39: =SUM(B39:M39) -> 4800 | O39: =N39/$N$2*100 -> 0.24308423
A40: Ciência | C40: 5166.6667 | D40: 5166.6667 | E40: 5166.6667 | N40: =SUM(B40:M40) -> 15500 | O40: =N40/$N$2*100 -> 0.7849595
A41: Tecnologia | I41: 1666.6667 | J41: 1666.6667 | K41: 1666.6667 | N41: =SUM(B41:M41) -> 5000 | O41: =N41/$N$2*100 -> 0.25321274
A42: Revisão ortográfica - 1º Ano Fund 1 | B42: =SUM(B43:B50) -> 0 | C42: =SUM(C43:C50) -> 0 | D42: =SUM(D43:D50) -> 0 | E42: =SUM(E43:E50) -> 0 | F42: =SUM(F43:F50) -> 0 | G42: =SUM(G43:G50) -> 0 | H42: =SUM(H43:H50) -> 0 | I42: =SUM(I43:I50) -> 1306.2346 | ... N42: =SUM(N43:N50) -> 2612.4693 | O42: =N42/$N$2*100 -> 0.1323021
A43: Português | I43: 163.27933 | J43: 163.27933 | N43: =SUM(B43:M43) -> 326.55866 | O43: =N43/$N$2*100 -> 0.016537763
A44: Matemática | I44: 163.27933 | J44: 163.27933 | N44: =SUM(B44:M44) -> 326.55866 | O44: =N44/$N$2*100 -> 0.016537763
A45: História | I45: 163.27933 | J45: 163.27933 | N45: =SUM(B45:M45) -> 326.55866 | O45: =N45/$N$2*100 -> 0.016537763
A46: Geografia | I46: 163.27933 | J46: 163.27933 | N46: =SUM(B46:M46) -> 326.55866 | O46: =N46/$N$2*100 -> 0.016537763
A47: Música | I47: 163.27933 | J47: 163.27933 | N47: =SUM(B47:M47) -> 326.55866 | O47: =N47/$N$2*100 -> 0.016537763
A48: Arte | I48: 163.27933 | J48: 163.27933 | N48: =SUM(B48:M48) -> 326.55866 | O48: =N48/$N$2*100 -> 0.016537763
A49: Ciência | I49: 163.27933 | J49: 163.27933 | N49: =SUM(B49:M49) -> 326.55866 | O49: =N49/$N$2*100 -> 0.016537763
A50: Tecnologia | I50: 163.27933 | J50: 163.27933 | N50: =SUM(B50:M50) -> 326.55866 | O50: =N50/$N$2*100 -> 0.016537763
A51: Ilustração - 1º Ano Fund 1 | B51: =SUM(B52:B59) -> 0 | C51: =SUM(C52:C59) -> 0 | D51: =SUM(D52:D59) -> 0 | E51: =SUM(E52:E59) -> 0 | F51: =SUM(F52:F59) -> 0 | G51: =SUM(G52:G59) -> 0 | H51: =SUM(H52:H59) -> 0 | I51: =SUM(I52:I59) -> 2500 | ... N51: =SUM(N52:N59) -> 5000 | O51: =N51/$N$2*100 -> 0.25321274
A52: Português | I52: 312.5 | J52: 312.5 | N52: =SUM(B52:M52) -> 625 | O52: =N52/$N$2*100 -> 0.031651593
A53: Matemática | I53: 312.5 | J53: 312.5 | N53: =SUM(B53:M53) -> 625 | O53: =N53/$N$2*100 -> 0.031651593
A54: História | I54: 312.5 | J54: 312.5 | N54: =SUM(B54:M54) -> 625 | O54: =N54/$N$2*100 -> 0.031651593
A55: Geografia | I55: 312.5 | J55: 312.5 | N55: =SUM(B55:M55) -> 625 | O55: =N55/$N$2*100 -> 0.031651593
A56: Música | I56: 312.5 | J56: 312.5 | N56: =SUM(B56:M56) -> 625 | O56: =N56/$N$2*100 -> 0.031651593
A57: Arte | I57: 312.5 | J57: 312.5 | N57: =SUM(B57:M57) -> 625 | O57: =N57/$N$2*100 -> 0.031651593
A58: Ciência | I58: 312.5 | J58: 312.5 | N58: =SUM(B58:M58) -> 625 | O58: =N58/$N$2*100 -> 0.031651593
A59: Tecnologia | I59: 312.5 | J59: 312.5 | N59: =SUM(B59:M59) -> 625 | O59: =N59/$N$2*100 -> 0.031651593
A60: Diagramação - 1º Ano Fund 1 | B60: =SUM(B61:B68) -> 0 | C60: =SUM(C61:C68) -> 0 | D60: =SUM(D61:D68) -> 0 | E60: =SUM(E61:E68) -> 0 | F60: =SUM(F61:F68) -> 0 | G60: =SUM(G61:G68) -> 0 | H60: =SUM(H61:H68) -> 0 | I60: =SUM(I61:I68) -> 4393.04 | ... N60: =SUM(N61:N68) -> 8786.08 | O60: =N60/$N$2*100 -> 0.44494948
A61: Português | I61: 549.13 | J61: 549.13 | N61: =SUM(B61:M61) -> 1098.26 | O61: =N61/$N$2*100 -> 0.055618685
A62: Matemática | I62: 549.13 | J62: 549.13 | N62: =SUM(B62:M62) -> 1098.26 | O62: =N62/$N$2*100 -> 0.055618685
A63: História | I63: 549.13 | J63: 549.13 | N63: =SUM(B63:M63) -> 1098.26 | O63: =N63/$N$2*100 -> 0.055618685
A64: Geografia | I64: 549.13 | J64: 549.13 | N64: =SUM(B64:M64) -> 1098.26 | O64: =N64/$N$2*100 -> 0.055618685
A65: Música | I65: 549.13 | J65: 549.13 | N65: =SUM(B65:M65) -> 1098.26 | O65: =N65/$N$2*100 -> 0.055618685
A66: Arte | I66: 549.13 | J66: 549.13 | N66: =SUM(B66:M66) -> 1098.26 | O66: =N66/$N$2*100 -> 0.055618685
A67: Ciência | I67: 549.13 | J67: 549.13 | N67: =SUM(B67:M67) -> 1098.26 | O67: =N67/$N$2*100 -> 0.055618685
A68: Tecnologia | I68: 549.13 | J68: 549.13 | N68: =SUM(B68:M68) -> 1098.26 | O68: =N68/$N$2*100 -> 0.055618685
A69: Livro do prof. (correção, ilust. e diagr.) - 1º Ano Fund 1 | B69: =SUM(B70:B76) -> 0 | C69: =SUM(C70:C76) -> 0 | D69: =SUM(D70:D76) -> 0 | E69: =SUM(E70:E76) -> 0 | F69: =SUM(F70:F76) -> 0 | G69: =SUM(G70:G76) -> 0 | H69: =SUM(H70:H76) -> 0 | I69: =SUM(I70:I76) -> 8596.57 | ... N69: =SUM(N70:N76) -> 17193.14 | O69: =N69/$N$2*100 -> 0.87070442
A70: Português | I70: 2178.57 | J70: 2178.57 | N70: =SUM(B70:M70) -> 4357.14 | O70: 0.22
A71: Matemática | I71: 1834.29 | J71: 1834.29 | N71: =SUM(B71:M71) -> 3668.58 | O71: 0.19
A72: História | I72: 636.14 | J72: 636.14 | N72: =SUM(B72:M72) -> 1272.28 | O72: 0.07
A73: Geografia | I73: 1359.43 | J73: 1359.43 | N73: =SUM(B73:M73) -> 2718.86 | O73: 0.14
A74: Música | I74: 714.57 | J74: 714.57 | N74: =SUM(B74:M74) -> 1429.14 | O74: 0.07
A75: Arte | I75: 714.57 | J75: 714.57 | N75: =SUM(B75:M75) -> 1429.14 | O75: 0.07
A76: Ciência | I76: 1159 | J76: 1159 | N76: =SUM(B76:M76) -> 2318
A77: Autoria - 2º Ano Fund 1 | B77: =SUM(B78:B85) -> 0 | C77: =SUM(C78:C85) -> 0 | D77: =SUM(D78:D85) -> 0 | E77: =SUM(E78:E85) -> 0 | F77: =SUM(F78:F85) -> 0 | G77: =SUM(G78:G85) -> 0 | H77: =SUM(H78:H85) -> 0 | I77: =SUM(I78:I85) -> 0 | ... N77: =SUM(N78:N85) -> 0 | O77: =N77/$N$2*100 -> 0
A78: Português | N78: =SUM(B78:M78) -> 0 | O78: =N78/$N$2*100 -> 0
A79: Matemática | N79: =SUM(B79:M79) -> 0 | O79: =N79/$N$2*100 -> 0
A80: História | N80: =SUM(B80:M80) -> 0 | O80: =N80/$N$2*100 -> 0
A81: Geografia | N81: =SUM(B81:M81) -> 0 | O81: =N81/$N$2*100 -> 0
A82: Música | N82: =SUM(B82:M82) -> 0 | O82: =N82/$N$2*100 -> 0
A83: Arte | N83: =SUM(B83:M83) -> 0 | O83: =N83/$N$2*100 -> 0
A84: Ciência | N84: =SUM(B84:M84) -> 0 | O84: =N84/$N$2*100 -> 0
A85: Tecnologia | N85: =SUM(B85:M85) -> 0 | O85: =N85/$N$2*100 -> 0
A86: Revisão ortográfica - 2º Ano Fund 1 | B86: =SUM(B87:B94) -> 0 | C86: =SUM(C87:C94) -> 0 | D86: =SUM(D87:D94) -> 0 | E86: =SUM(E87:E94) -> 0 | F86: =SUM(F87:F94) -> 0 | G86: =SUM(G87:G94) -> 0 | H86: =SUM(H87:H94) -> 0 | I86: =SUM(I87:I94) -> 5687.5393 | ... N86: =SUM(N87:N94) -> 5687.5393 | O86: =N86/$N$2*100 -> 0.28803148
A87: Português | I87: 1086.4929 | N87: =SUM(B87:M87) -> 1086.4929 | O87: =N87/$N$2*100 -> 0.055022767
A88: Matemática | I88: 851.48571 | N88: =SUM(B88:M88) -> 851.48571 | O88: =N88/$N$2*100 -> 0.043121406
A89: História | I89: 716.99643 | N89: =SUM(B89:M89) -> 716.99643 | O89: =N89/$N$2*100 -> 0.036310526
A90: Geografia | I90: 1192.5143 | N90: =SUM(B90:M90) -> 1192.5143 | O90: =N90/$N$2*100 -> 0.060391962
A91: Música | I91: 314.75714 | N91: =SUM(B91:M91) -> 314.75714 | O91: =N91/$N$2*100 -> 0.015940104
A92: Arte | I92: 314.75714 | N92: =SUM(B92:M92) -> 314.75714 | O92: =N92/$N$2*100 -> 0.015940104
A93: Ciência | I93: 673.63929 | N93: =SUM(B93:M93) -> 673.63929 | O93: =N93/$N$2*100 -> 0.03411481
A94: Tecnologia | I94: 536.89643 | N94: =SUM(B94:M94) -> 536.89643 | O94: =N94/$N$2*100 -> 0.027189803
A95: Ilustração - 2º Ano Fund 1 | B95: =SUM(B96:B103) -> 0 | C95: =SUM(C96:C103) -> 0 | D95: =SUM(D96:D103) -> 0 | E95: =SUM(E96:E103) -> 0 | F95: =SUM(F96:F103) -> 0 | G95: =SUM(G96:G103) -> 0 | H95: =SUM(H96:H103) -> 0 | I95: =SUM(I96:I103) -> 2000 | ... N95: =SUM(N96:N103) -> 6000 | O95: =N95/$N$2*100 -> 0.30385529
A96: Português | I96: 400 | J96: 400 | K96: 400 | N96: =SUM(B96:M96) -> 1200 | O96: =N96/$N$2*100 -> 0.060771058
A97: Matemática | I97: 400 | J97: 400 | K97: 400 | N97: =SUM(B97:M97) -> 1200 | O97: =N97/$N$2*100 -> 0.060771058
A98: História | I98: 200 | J98: 200 | K98: 200 | N98: =SUM(B98:M98) -> 600 | O98: =N98/$N$2*100 -> 0.030385529
A99: Geografia | I99: 200 | J99: 200 | K99: 200 | N99: =SUM(B99:M99) -> 600 | O99: =N99/$N$2*100 -> 0.030385529
A100: Música | I100: 200 | J100: 200 | K100: 200 | N100: =SUM(B100:M100) -> 600 | O100: =N100/$N$2*100 -> 0.030385529
A101: Arte | I101: 200 | J101: 200 | K101: 200 | N101: =SUM(B101:M101) -> 600 | O101: =N101/$N$2*100 -> 0.030385529
...
